rerun_notebook/__init__.py
rerun_notebook/__main__.py
rerun_notebook/asset_server.py
rerun_notebook/error_widget.js
rerun_notebook/static/re_viewer_bg.wasm
rerun_notebook/static/widget.css
rerun_notebook/static/widget.js
rerun_notebook-0.29.0.dist-info/METADATA
rerun_notebook-0.29.0.dist-info/WHEEL
rerun_notebook-0.29.0.dist-info/RECORD
