Metadata-Version: 2.4
Name: rerun-notebook
Version: 0.29.0
Summary: Implementation helper for running rerun-sdk in notebooks
Author-email: "Rerun.io" <opensource@rerun.io>
License: MIT OR Apache-2.0
Keywords: notebook,rerun
Requires-Dist: anywidget
Requires-Dist: ipykernel<7.0.0
Requires-Dist: jupyter-ui-poll
Provides-Extra: dev
Requires-Dist: hatch; extra == 'dev'
Requires-Dist: jupyterlab; extra == 'dev'
Requires-Dist: watchfiles; extra == 'dev'
